MANIFEST.in
chariot.conf
setup.py
chariot_runtime.egg-info/PKG-INFO
chariot_runtime.egg-info/SOURCES.txt
chariot_runtime.egg-info/dependency_links.txt
chariot_runtime.egg-info/not-zip-safe
chariot_runtime.egg-info/requires.txt
chariot_runtime.egg-info/top_level.txt
chariot_runtime_libs/__init__.py
chariot_runtime_libs/chariot_helpers.py
chariot_runtime_libs/configuration_solver.py
chariot_runtime_libs/deployment_manager.py
chariot_runtime_libs/logger.py
chariot_runtime_libs/management_engine.py
chariot_runtime_libs/new_configuration_solver.py
chariot_runtime_libs/new_configuration_solver_bound.py
chariot_runtime_libs/solver_backend.py
init_scripts/chariot-dm
init_scripts/chariot-nm
init_scripts/chariot-nmw
scripts/chariot-dm
scripts/chariot-me
scripts/chariot-nm
scripts/chariot-nmw
scripts/chariot-rm
scripts/chariot-sna