Metadata-Version: 1.0
Name: chariot-runtime
Version: 0.0.5
Summary: CHARIOT Runtime Package (Beta)
Home-page: https://github.com/visor-vu/chariot
Author: visor-vu
Author-email: visorvu@gmail.com
License: MIT
Platform: UNKNOWN
